setup.py
who_name/__init__.py
who_name.egg-info/PKG-INFO
who_name.egg-info/SOURCES.txt
who_name.egg-info/dependency_links.txt
who_name.egg-info/not-zip-safe
who_name.egg-info/top_level.txt