Metadata-Version: 1.0
Name: who-name
Version: 0.5
Summary: just praticse
Home-page: UNKNOWN
Author: idk
Author-email: idk@gmail.com
License: UNKNOWN
Platform: UNKNOWN
